yandex_image_scraper-0.15.0.dist-info/METADATA
yandex_image_scraper-0.15.0.dist-info/WHEEL
yandex_image_scraper-0.15.0.dist-info/entry_points.txt
yandex_image_scraper-0.15.0.dist-info/licenses/LICENSE.txt
yandex_image_scraper/__init__.py
yandex_image_scraper/main.py
yandex_image_scraper/spoofing.py
yandex_image_scraper/tor_handler.py
yandex_image_scraper-0.15.0.dist-info/RECORD
