Metadata-Version: 2.1
Name: yandex-image-scraper
Version: 0.15.0
Summary: A command-line tool to scrape and download images from Yandex search results
Author-Email: Tadeas Fort <business@tadeasfort.com>
License: GPL-3.0
Requires-Python: >=3.8
Requires-Dist: camoufox[geoip]==0.4.11
Requires-Dist: playwright==1.51.0
Requires-Dist: aiohttp>=3.11.14
Requires-Dist: typer>=0.15.2
Requires-Dist: prompt-toolkit>=3.0.50
